{"tickers":[{"ask":"0.7400000000","base_currency":"KUJI","base_volume":"79067.9811390000","bid":"0.7370000000","high":"0.7630000000","last_price":"0.7370000208","low":"0.7220000008","pool_id":"kujira14hj2tavq8fpesdwxxcu44rty3hh90vhujrvcmstl4zr3txmfvw9sl4e867","target_currency":"axlUSDC","target_volume":"58905.2622640000","ticker_id":"KUJI_axlUSDC"},{"ask":"7.8920000000","base_currency":"INJ","base_volume":"2.7556416497","bid":"7.7480000000","high":"8.0339946248","last_price":"7.8919921080","low":"7.6950000000","pool_id":"kujira1ddeadmhum3umygv84frhc87gl2grzjmx9x8fuhjts7zqwuc39xuq53w3d8","target_currency":"USK","target_volume":"21.6463560000","ticker_id":"INJ_USK"},{"ask":"1860.5600000000","base_currency":"wETH","base_volume":"0.1502975188","bid":"1812.6500000000","high":"1860.4748873866","last_price":"1860.4748873866","low":"1823.4900000000","pool_id":"kujira1suhgf5svhu4usrurvxzlgn54ksxmn8gljarjtxqnapv8kjnp4nrsqq4jjh","target_currency":"axlUSDC","target_volume":"275.1993020000","ticker_id":"wETH_axlUSDC"},{"ask":"1789.5200000000","base_currency":"wETH","base_volume":"0.0497361124","bid":"1743.4300000000","high":"1821.3097250567","last_price":"1778.8400000000","low":"1778.8400000000","pool_id":"kujira17w9r23r8v8r7z5lphwj99296fhlye9ej5nq3hlqw554u63m88avspdl9tc","target_currency":"USK","target_volume":"89.0260150000","ticker_id":"wETH_USK"},{"ask":"244.4330000000","base_currency":"wBNB","base_volume":"2.0498105927","bid":"243.4570000000","high":"254.9999930654","last_price":"241.2669257721","low":"11.1500000000","pool_id":"kujira1apkgj87fgfsq84swvkyfaemrq7t4deuh60887lek0hkgdjh5fj0qaz7fhx","target_currency":"axlUSDC","target_volume":"359.9996170000","ticker_id":"wBNB_axlUSDC"},{"ask":"0.0610000000","base_currency":"CNTO","base_volume":"0.0000000000","bid":"0.0590000000","high":"715001430002.8600000000","last_price":"715001430002.8600000000","low":"715001430002.8600000000","pool_id":"kujira1642dp8q7gzm5g5csdz2k676rc5zqfka4hfnas9ffydffp0saspts0e9zgp","target_currency":"USK","target_volume":"0.0000000000","ticker_id":"CNTO_USK"},{"ask":"0.0000000000","base_currency":"PLQ","base_volume":"0.0000000000","bid":"0.0000000000","high":"8.4660097477","last_price":"8.4660097477","low":"8.4660097477","pool_id":"kujira1q7p9wldxxvnqda4hx8w6caplqj33tfxne5efjamsp6ruhuk3knwqwjuhrn","target_currency":"USK","target_volume":"0.0000000000","ticker_id":"PLQ_USK"},{"ask":"25.0000000000","base_currency":"FRIENZIES","base_volume":"0.0000000000","bid":"24.7087000000","high":"8.4660097477","last_price":"8.4660097477","low":"8.4660097477","pool_id":"kujira1e8z7d334ngww7lnqaczlcrjpwg9hc5ggcptkk7nvc7ld4tem6dgsm9h336","target_currency":"ATOM","target_volume":"0.0000000000","ticker_id":"FRIENZIES_ATOM"},{"ask":"0.2420000000","base_currency":"wFTM","base_volume":"0.0000000000","bid":"0.2390000000","high":"8466009747695.6870000000","last_price":"8466009747695.6870000000","low":"8466009747695.6870000000","pool_id":"kujira1ky9kv2m4dnykm90d0lj5089k4efttgfpx34zyvkklxnew48c522sggqjsg","target_currency":"USK","target_volume":"0.0000000000","ticker_id":"wFTM_USK"},{"ask":"1.0043000000","base_currency":"ampKUJI","base_volume":"299.1251570000","bid":"1.0004000000","high":"1.0042999975","last_price":"1.0042999975","low":"1.0001000893","pool_id":"kujira1lse59wt7a5yksdd08mennt299katjkfzdhmh8hvck8ln08jktcmsxrnh8s","target_currency":"KUJI","target_volume":"300.4096740000","ticker_id":"ampKUJI_KUJI"},{"ask":"0.1427000000","base_currency":"MNTA","base_volume":"35527.2958540000","bid":"0.1396000000","high":"0.1448994466","last_price":"0.1396001396","low":"0.1361000004","pool_id":"kujira1mf4v3x3pkuthha5a4r9jd0slgulcxkucy4weuqsvx2n030twduzqewuznf","target_currency":"USK","target_volume":"4977.9213490000","ticker_id":"MNTA_USK"},{"ask":"0.0000012202","base_currency":"ROAR","base_volume":"394063749.7979630000","bid":"0.0000011935","high":"0.0000012680","last_price":"0.0000012171","low":"0.0000012171","pool_id":"kujira1vllmvr0ylegpgg34y727kmys4yy3kjjnwj8xt3j22mdc5u4z7egs5d0sg8","target_currency":"USK","target_volume":"486.5665600000","ticker_id":"ROAR_USK"},{"ask":"58.3300000000","base_currency":"TAO","base_volume":"0.0484298610","bid":"57.0600000000","high":"58.2700056533","last_price":"56.0399848662","low":"55.9200040821","pool_id":"kujira17qp8g5n5wwelrsnfdakrv0p550nzg72agpcz5t0ea6thlqd300hquxljcc","target_currency":"axlUSDC","target_volume":"2.7550570000","ticker_id":"TAO_axlUSDC"},{"ask":"56.8500000000","base_currency":"TAO","base_volume":"0.7287456380","bid":"55.6000000000","high":"59.3798007136","last_price":"56.7598618777","low":"54.0000002475","pool_id":"kujira1538ukswznmuek3hfv7mcxem9hjqz8sa4ypl2ul0zncu3tdgfvwmq8pxkwp","target_currency":"USK","target_volume":"40.7845990000","ticker_id":"TAO_USK"},{"ask":"0.0169800000","base_currency":"WHALE","base_volume":"140.5488930000","bid":"0.0166100000","high":"0.0169599831","last_price":"0.0169599831","low":"0.0166000003","pool_id":"kujira1x38mke7q0qut5lku4zrx7wgjrsj9jn3tffadegzzcsy9s5w5mdmqzzl0sn","target_currency":"USK","target_volume":"2.3547570000","ticker_id":"WHALE_USK"},{"ask":"0.1000000000","base_currency":"EVMOS","base_volume":"0.0000000000","bid":"0.0950000000","high":"715001430002.8600000000","last_price":"715001430002.8600000000","low":"715001430002.8600000000","pool_id":"kujira182nff4ttmvshn6yjlqj5czapfcav9434l2qzz8aahf5pxnyd33tsz30aw6","target_currency":"axlUSDC","target_volume":"0.0000000000","ticker_id":"EVMOS_axlUSDC"},{"ask":"0.0000730000","base_currency":"LUNA","base_volume":"113032.0842270000","bid":"0.0000710000","high":"0.0000750000","last_price":"0.0000720000","low":"0.0000720000","pool_id":"kujira10lzmqlvey89gwd4jz8aq3s4xdllk2k56yj45cex9s86v8g7nkpmq24djj4","target_currency":"USK","target_volume":"8.3143100000","ticker_id":"LUNA_USK"},{"ask":"7.7980000000","base_currency":"LINK","base_volume":"0.0000000000","bid":"7.7050000000","high":"715001430002.8600000000","last_price":"715001430002.8600000000","low":"715001430002.8600000000","pool_id":"kujira12zjpumtfh88k6s2s8k4wks37ezr2c3zeha5xx6qpd65e5ehz50nq0afvrv","target_currency":"USK","target_volume":"0.0000000000","ticker_id":"LINK_USK"},{"ask":"0.7210000000","base_currency":"KUJI","base_volume":"14332.3154900000","bid":"0.7150000000","high":"0.7529999978","last_price":"0.7150017875","low":"0.7150000012","pool_id":"kujira193dzcmy7lwuj4eda3zpwwt9ejal00xva0vawcvhgsyyp5cfh6jyq66wfrf","target_currency":"USK","target_volume":"10513.8874760000","ticker_id":"KUJI_USK"},{"ask":"0.0000000004","base_currency":"PEPE","base_volume":"0.0000000000","bid":"0.0000000002","high":"8.1940568957","last_price":"8.1940568957","low":"8.1940568957","pool_id":"kujira1ykrjmez7razkdfj695uhu5kuxcdxjgyatmzuz63ujrfddzcrrr8suzsxtk","target_currency":"wETH","target_volume":"0.0000000000","ticker_id":"PEPE_wETH"},{"ask":"1900.7200000000","base_currency":"PAXG","base_volume":"0.0891447973","bid":"1878.0000000000","high":"1921.4787190133","last_price":"1879.7700000000","low":"1879.7700000000","pool_id":"kujira1rtpn4nxkx7u5y4uf5lp4ywrhmnms07p8p8wc3pmw53hfv0lhyxdqlfhgrt","target_currency":"USK","target_volume":"169.1528610000","ticker_id":"PAXG_USK"},{"ask":"0.7460000000","base_currency":"wMATIC","base_volume":"0.0000000000","bid":"0.7370000000","high":"971893934639.9760000000","last_price":"971893934639.9760000000","low":"971893934639.9760000000","pool_id":"kujira1rrnacml8zeqq3ve2t98r5x88t4uahahdk66y9qpcrjp9qxhnuvysv59zx8","target_currency":"USK","target_volume":"0.0000000000","ticker_id":"wMATIC_USK"},{"ask":"0.7970000000","base_currency":"STRD","base_volume":"215.2151940000","bid":"0.7940000000","high":"0.8239925892","last_price":"0.7919998524","low":"0.7830000525","pool_id":"kujira1cn922pcqrt4g2dr4va9vxk8h3w3jfxnxjqq2qp6zktjsehdzde6sz66um0","target_currency":"USK","target_volume":"173.5078310000","ticker_id":"STRD_USK"},{"ask":"0.9719000000","base_currency":"axlUSDC","base_volume":"60510.5861630000","bid":"0.9681000000","high":"0.9823999982","last_price":"0.9718939346","low":"0.9195000022","pool_id":"kujira1rwx6w02alc4kaz7xpyg3rlxpjl4g63x5jq292mkxgg65zqpn5llq202vh5","target_currency":"USK","target_volume":"58205.1297680000","ticker_id":"axlUSDC_USK"},{"ask":"1.4000000000","base_currency":"ARB","base_volume":"0.0000000000","bid":"1.3770000000","high":"545000049619.3974000000","last_price":"545000049619.3974000000","low":"545000049619.3974000000","pool_id":"kujira1zf94p6srpmlk0d5p9pwpqqwztynd22mndqljqvral604k8jfcw4sw2y7kp","target_currency":"USK","target_volume":"0.0000000000","ticker_id":"ARB_USK"},{"ask":"22.0000000000","base_currency":"wAVAX","base_volume":"0.0000000000","bid":"9.0310000000","high":"8466009747695.6870000000","last_price":"8466009747695.6870000000","low":"8466009747695.6870000000","pool_id":"kujira1qjxu65ucccpg8c5kac8ng6yxfqq85fluwd0p9nt74g2304qw8eyq930y7w","target_currency":"axlUSDC","target_volume":"0.0000000000","ticker_id":"wAVAX_axlUSDC"},{"ask":"10.7900000000","base_currency":"wAVAX","base_volume":"0.0000000000","bid":"10.6620000000","high":"968200043031.1130000000","last_price":"968200043031.1130000000","low":"968200043031.1130000000","pool_id":"kujira1fphguznhazgqdlr9mpfh6nmn3vjjr73ksz3ukznv6q7s9ndfq2cs8vhapj","target_currency":"USK","target_volume":"0.0000000000","ticker_id":"wAVAX_USK"},{"ask":"8.4980000000","base_currency":"ATOM","base_volume":"2153.9403760000","bid":"8.4640000000","high":"9.2620238259","last_price":"8.4660097477","low":"8.4229999918","pool_id":"kujira1xr3rq8yvd7qplsw5yx90ftsr2zdhg4e9z60h5duusgxpv72hud3sl8nek6","target_currency":"axlUSDC","target_volume":"18640.3905960000","ticker_id":"ATOM_axlUSDC"},{"ask":"8.2260000000","base_currency":"ATOM","base_volume":"860.3394800000","bid":"8.1930000000","high":"8.4959999893","last_price":"8.1940568957","low":"8.1340053005","pool_id":"kujira1yum4v0v5l92jkxn8xpn9mjg7wuldk784ctg424ue8gqvdp88qzlqr2qp2j","target_currency":"USK","target_volume":"7120.2197030000","ticker_id":"ATOM_USK"},{"ask":"0.2410000000","base_currency":"JUNO","base_volume":"40029.3831570000","bid":"0.2370000000","high":"0.2549999997","last_price":"0.2370000963","low":"0.2120000424","pool_id":"kujira1z7asfxkwv0t863rllul570eh5pf2zk07k3d86ag4vtghaue37l5s9epdvn","target_currency":"axlUSDC","target_volume":"9240.3534870000","ticker_id":"JUNO_axlUSDC"},{"ask":"0.5510000000","base_currency":"LUNA","base_volume":"90.5551500000","bid":"0.5500000000","high":"0.5510000084","last_price":"0.5500000104","low":"0.5500000104","pool_id":"kujira1yg8930mj8pk288lmkjex0qz85mj8wgtns5uzwyn2hs25pwdnw42skp0kur","target_currency":"axlUSDC","target_volume":"49.8432400000","ticker_id":"LUNA_axlUSDC"},{"ask":"1.0050000000","base_currency":"axlUSDT","base_volume":"0.0000000000","bid":"0.9501000000","high":"8.1940568957","last_price":"8.1940568957","low":"8.1940568957","pool_id":"kujira1xut80d09q0tgtch8p0z4k5f88d3uvt8cvtzm5h3tu3tsy4jk9xlscem692","target_currency":"axlUSDC","target_volume":"0.0000000000","ticker_id":"axlUSDT_axlUSDC"},{"ask":"0.4200000000","base_currency":"SCRT","base_volume":"0.0000000000","bid":"0.2000000000","high":"0.9682000430","last_price":"0.9682000430","low":"0.9682000430","pool_id":"kujira1fkwjqyfdyktgu5f59jpwhvl23zh8aav7f98ml9quly62jx2sehysqa4unf","target_currency":"axlUSDC","target_volume":"0.0000000000","ticker_id":"SCRT_axlUSDC"},{"ask":"0.3320000000","base_currency":"SCRT","base_volume":"441.7768590000","bid":"0.3310000000","high":"0.3530001671","last_price":"0.3350000626","low":"0.3080032505","pool_id":"kujira1rpxf55u22q2tly9y8rgdrjgx9p52sus7jugaevj3hdt0z7sgvkcsyrhrv0","target_currency":"USK","target_volume":"148.2466080000","ticker_id":"SCRT_USK"},{"ask":"0.4440000000","base_currency":"OSMO","base_volume":"43.1727290000","bid":"0.4420000000","high":"0.4559961254","last_price":"0.4510005552","low":"0.4319985246","pool_id":"kujira1w2l4w5p66l5t2nmrmsvz7k4cu50s7e8dc6h59gcxsnmp2tgy7q7s5lux8a","target_currency":"USK","target_volume":"19.1159610000","ticker_id":"OSMO_USK"},{"ask":"0.0100000000","base_currency":"STARS","base_volume":"20901.6000490000","bid":"0.0098000000","high":"0.0102000000","last_price":"0.0098000002","low":"0.0097999995","pool_id":"kujira1nm3yktzcgpnvwu6qpzqgl2ktyvlgsstc7ev849dd3ulaygw75mqqxvtnck","target_currency":"USK","target_volume":"210.0435920000","ticker_id":"STARS_USK"},{"ask":"7.9280000000","base_currency":"SHD","base_volume":"0.0000000000","bid":"7.9190000000","high":"96.8200043031","last_price":"96.8200043031","low":"96.8200043031","pool_id":"kujira1cduudfszcm9slm8qxlaqvnpzg2u0hkus94fe3pwt9x446dtw6eeql8ualz","target_currency":"USK","target_volume":"0.0000000000","ticker_id":"SHD_USK"},{"ask":"0.2550000000","base_currency":"JUNO","base_volume":"0.0000000000","bid":"0.2540000000","high":"0.5450000496","last_price":"0.5450000496","low":"0.5450000496","pool_id":"kujira1z7quf5t6g7spjnu2qhcp2x2ksnz4zfut9k73uutpg2q95dd008fqsprtvl","target_currency":"USK","target_volume":"0.0000000000","ticker_id":"JUNO_USK"},{"ask":"0.0003000000","base_currency":"FURY","base_volume":"103577.5444020000","bid":"0.0002900000","high":"0.0002900000","last_price":"0.0002200000","low":"0.0002099999","pool_id":"kujira1v8lkqws3gd6npr0rdk9ch54amh9guas86r4u62jq27hee88lryfsxwrvlk","target_currency":"USK","target_volume":"26.2269050000","ticker_id":"FURY_USK"},{"ask":"0.3963000000","base_currency":"AXL","base_volume":"0.0000000000","bid":"0.3916000000","high":"8.4660097477","last_price":"8.4660097477","low":"8.4660097477","pool_id":"kujira1dtaqwlmzlk3jku5un6h6rfunttmwsqnfz7evvdf4pwr0wypsl68q49aaud","target_currency":"USK","target_volume":"0.0000000000","ticker_id":"AXL_USK"},{"ask":"4.9130000000","base_currency":"DOT","base_volume":"2.0053562885","bid":"4.8500000000","high":"4.8500000541","last_price":"4.8500000002","low":"4.8500000002","pool_id":"kujira1jlzw6xal0n2c580g3wxs09tjhlzdht9y8dgszq3tupf8fhl7xjus7ep7ap","target_currency":"USK","target_volume":"9.7259780000","ticker_id":"DOT_USK"},{"ask":"0.0300000000","base_currency":"ASTRO","base_volume":"0.0000000000","bid":"0.0170000000","high":"8.4660097477","last_price":"8.4660097477","low":"8.4660097477","pool_id":"kujira1qqlk2773dvj8cyv3ftnzvyrknq78yryghp3uyumnumaxu656yreszrdph0","target_currency":"USK","target_volume":"0.0000000000","ticker_id":"ASTRO_USK"},{"ask":"0.0882000000","base_currency":"KUJI","base_volume":"27007.6411550000","bid":"0.0864000000","high":"0.0911993904","last_price":"0.0881999977","low":"0.0851000028","pool_id":"kujira18v47nqmhvejx3vc498pantg8vr435xa0rt6x0m6kzhp6yuqmcp8s4x8j2c","target_currency":"ATOM","target_volume":"2365.2040190000","ticker_id":"KUJI_ATOM"},{"ask":"24.3910000000","base_currency":"ATOM","base_volume":"0.0000000000","bid":"23.3910000000","high":"0.0020299949","last_price":"0.0020299949","low":"0.0020299949","pool_id":"kujira1hulx7cgvpfcvg83wk5h96sedqgn72n026w6nl47uht554xhvj9nsra5j5u","target_currency":"OSMO","target_volume":"0.0000000000","ticker_id":"ATOM_OSMO"},{"ask":"0.6540000000","base_currency":"ampLUNA","base_volume":"0.0000000000","bid":"0.6510000000","high":"8.1940568957","last_price":"8.1940568957","low":"8.1940568957","pool_id":"kujira1uvqk5vj9vn4gjemrp0myz4ku49aaemulgaqw7pfe0nuvfwp3gukq64r3ws","target_currency":"USK","target_volume":"0.0000000000","ticker_id":"ampLUNA_USK"},{"ask":"0.5470000000","base_currency":"LUNA","base_volume":"1571.7335190000","bid":"0.5450000000","high":"0.5530002060","last_price":"0.5450000496","low":"0.5410000108","pool_id":"kujira1zz74gvmq6ss3pg5vgahvx47ugpfzr80qu75l97lf2ggdgxq04ddqxkdzey","target_currency":"USK","target_volume":"860.6969320000","ticker_id":"LUNA_USK"},{"ask":"0.8660000000","base_currency":"LP-KUJI-ATOM","base_volume":"203.5049530000","bid":"0.3000000000","high":"0.3150000027","last_price":"0.0360000001","low":"0.0360000001","pool_id":"kujira1gl8js9zn7h9u2h37fx7qg8xy65jrk9t4zpa6s7j5hdlanud2uwxshqq67m","target_currency":"ATOM","target_volume":"35.3701190000","ticker_id":"LP-KUJI-ATOM_ATOM"},{"ask":"0.0120000000","base_currency":"STARS","base_volume":"6.7178170000","bid":"0.0090000000","high":"0.0110000011","last_price":"0.0090000072","low":"0.0090000072","pool_id":"kujira1jkte0pytr85qg0whmgux3vmz9ehmh82w40h8gaqeg435fnkyfxqq5m32qy","target_currency":"axlUSDC","target_volume":"0.0677080000","ticker_id":"STARS_axlUSDC"},{"ask":"13.5720000000","base_currency":"LP-KUJI-ATOM","base_volume":"6.6312990000","bid":"5.5010000000","high":"13.5719999958","last_price":"13.5719999958","low":"13.5719999958","pool_id":"kujira1hs95lgvuy0p6jn4v7js5x8plfdqw867lsuh5xv6d2ua20jprkgesw2pujt","target_currency":"KUJI","target_volume":"89.9999900000","ticker_id":"LP-KUJI-ATOM_KUJI"},{"ask":"5.0390000000","base_currency":"DOT","base_volume":"0.0000000000","bid":"4.9090000000","high":"81940.5689571604","last_price":"81940.5689571604","low":"81940.5689571604","pool_id":"kujira1w4t2qpwvhyhz0g2mwgqjzgsw63dcy5hkfch0tgr8xj9qjcsauq8q5x0zxz","target_currency":"axlUSDC","target_volume":"0.0000000000","ticker_id":"DOT_axlUSDC"},{"ask":"0.0014000000","base_currency":"LOOP","base_volume":"0.0000000000","bid":"0.0012000000","high":"0.7150014300","last_price":"0.7150014300","low":"0.7150014300","pool_id":"kujira10fqy0npt7djm8lg847v9rqlng88kqfdvl8tyt4ge204wf52sy68qwmj07l","target_currency":"axlUSDC","target_volume":"0.0000000000","ticker_id":"LOOP_axlUSDC"},{"ask":"0.0690000000","base_currency":"CMDX","base_volume":"0.0000000000","bid":"0.0300000000","high":"0.7150014300","last_price":"0.7150014300","low":"0.7150014300","pool_id":"kujira16y344e8ryydmeu2g8yyfznq79j7jfnar4p59ngpvaazcj83jzsms6tju67","target_currency":"axlUSDC","target_volume":"0.0000000000","ticker_id":"CMDX_axlUSDC"},{"ask":"0.5310000000","base_currency":"OSMO","base_volume":"1624.8156910000","bid":"0.4480000000","high":"0.5319999864","last_price":"0.4480014274","low":"0.4480000003","pool_id":"kujira1aakfpghcanxtc45gpqlx8j3rq0zcpyf49qmhm9mdjrfx036h4z5sfmexun","target_currency":"axlUSDC","target_volume":"740.9397670000","ticker_id":"OSMO_axlUSDC"},{"ask":"1.3290000000","base_currency":"KUJI","base_volume":"192.2632270000","bid":"1.3140000000","high":"1.3699994997","last_price":"1.3270000936","low":"1.3090000170","pool_id":"kujira1xqhakgvn3jeqfade0z4aufer9xylx7ft45fgyhg6z75mauhkjwks9cucyq","target_currency":"LUNA","target_volume":"254.8114900000","ticker_id":"KUJI_LUNA"},{"ask":"0.0006600000","base_currency":"CRO","base_volume":"0.0000000000","bid":"0.0006580000","high":"0.7150014300","last_price":"0.7150014300","low":"0.7150014300","pool_id":"kujira10j648ftg2g8p5vhgsu5kzfh6d907vpkrn0a5l3qch479eqy2qssqm905c4","target_currency":"USK","target_volume":"0.0000000000","ticker_id":"CRO_USK"},{"ask":"0.0080500000","base_currency":"LOCAL","base_volume":"506.2454000000","bid":"0.0080400000","high":"0.0082000000","last_price":"0.0080400000","low":"0.0080400000","pool_id":"kujira1sse6a00arh9dalzsyrd3q825dsn2zmrag0u4qx8q0dyks4ftnxyqrj0xds","target_currency":"USK","target_volume":"4.1106630000","ticker_id":"LOCAL_USK"},{"ask":"0.0010500000","base_currency":"LOOP","base_volume":"308.9999990000","bid":"0.0010400000","high":"0.0010400000","last_price":"0.0010400000","low":"0.0010400000","pool_id":"kujira1k7rg9vscg2uldw6868mecryxhlze5e3f4z0f00295ddu7cz3l4ws4d9dfj","target_currency":"USK","target_volume":"0.3213600000","ticker_id":"LOOP_USK"},{"ask":"0.9918000000","base_currency":"CMST","base_volume":"0.0000000000","bid":"0.9845000000","high":"8.4660097477","last_price":"8.4660097477","low":"8.4660097477","pool_id":"kujira1qw5hdcmcf4aq5xmnu6znscurvkgvhxfsyvhz3jvxhasxjwtk3l7sccwcs8","target_currency":"USK","target_volume":"0.0000000000","ticker_id":"CMST_USK"},{"ask":"0.0267000000","base_currency":"CMDX","base_volume":"0.0000000000","bid":"0.0264000000","high":"8.4660097477","last_price":"8.4660097477","low":"8.4660097477","pool_id":"kujira1h7eenquygffwsmc8csrlx88zcddwx0aqspq3x2dsl20lwk4r9n2q9t86ht","target_currency":"USK","target_volume":"0.0000000000","ticker_id":"CMDX_USK"},{"ask":"28690.9400000000","base_currency":"wBTC","base_volume":"0.0000000000","bid":"28063.9000000000","high":"819.4056895716","last_price":"819.4056895716","low":"819.4056895716","pool_id":"kujira1ulyrqqtx9vqsk92805jk7xxwz77lszmm2f548juyced96tj4lg7qugewsf","target_currency":"USK","target_volume":"0.0000000000","ticker_id":"wBTC_USK"},{"ask":"1.0060000000","base_currency":"DAI","base_volume":"0.0109388511","bid":"0.9714000000","high":"0.9714000000","last_price":"0.9714000000","low":"0.9714000000","pool_id":"kujira18lm235jzuh4t7hh5z8lqyz08dmz67magj8z0fc4a0vn6c0hzk0es3r4glx","target_currency":"USK","target_volume":"0.0106260000","ticker_id":"DAI_USK"},{"ask":"1961.5300000000","base_currency":"PAXG","base_volume":"0.1813363142","bid":"1941.9600000000","high":"1968.7499875048","last_price":"1961.5300000000","low":"1961.5300000000","pool_id":"kujira12p30cr4gstmp2yucwxtaq92turrzsxxar8upz3rhmfjxh6gdgk4s5vsyse","target_currency":"axlUSDC","target_volume":"356.3086640000","ticker_id":"PAXG_axlUSDC"},{"ask":"1.1850000000","base_currency":"stATOM","base_volume":"120.3629390000","bid":"1.1769000000","high":"1.1916998946","last_price":"1.1888044628","low":"1.1500000192","pool_id":"kujira158zzjcvkz7r3j5hueurcw22qrjerqw4dtrzlalztr7whjykjwvrsrahdnq","target_currency":"ATOM","target_volume":"140.3830730000","ticker_id":"stATOM_ATOM"},{"ask":"1.2107000000","base_currency":"ampLUNA","base_volume":"0.0000000000","bid":"1.2027000000","high":"0.7209999386","last_price":"0.7209999386","low":"0.7209999386","pool_id":"kujira172qjrk8g9l86w0shz4cc3e6rt5h9janaen4j4u6ze7xkjvjnaqfskwyyqm","target_currency":"LUNA","target_volume":"0.0000000000","ticker_id":"ampLUNA_LUNA"},{"ask":"0.0621000000","base_currency":"MARS","base_volume":"414.9970260000","bid":"0.0614000000","high":"0.0620999882","last_price":"0.0619999911","low":"0.0608999951","pool_id":"kujira1v8kh6mqxq7awcvl936xeyzv8fnmdkd3yxggvkyek5d0ecut4a6zs0larj2","target_currency":"USK","target_volume":"25.5543300000","ticker_id":"MARS_USK"},{"ask":"0.0640000000","base_currency":"MARS","base_volume":"2008.0420280000","bid":"0.0635000000","high":"0.0640000005","last_price":"0.0640000005","low":"0.0620999991","pool_id":"kujira149m52kn7nvsg5nftvv4fh85scsavpdfxp5nr7zasz97dum89dp5qevttd9","target_currency":"axlUSDC","target_volume":"127.0585720000","ticker_id":"MARS_axlUSDC"},{"ask":"90.6910000000","base_currency":"KUJI","base_volume":"5.6296670000","bid":"88.7090000000","high":"90.4520484059","last_price":"89.8700236835","low":"89.8700236835","pool_id":"kujira17v40udkwtm9tt2wt73ejj6xh9x4ts8at6zv6nhmusdj4x6ffnl2qpep73h","target_currency":"LOCAL","target_volume":"507.0228090000","ticker_id":"KUJI_LOCAL"},{"ask":"10.1160000000","base_currency":"stATOM","base_volume":"3.4829090000","bid":"9.8960000000","high":"10.2369985889","last_price":"10.0489979383","low":"9.8961635366","pool_id":"kujira18rd5fge3m8zvcw4rl94ztre2jra0srpv8d7t64aag4gzw7jkmzeqvx564r","target_currency":"USK","target_volume":"35.4278020000","ticker_id":"stATOM_USK"},{"ask":"0.0741000000","base_currency":"KUJI","base_volume":"11.4880370000","bid":"0.0725000000","high":"0.0753000251","last_price":"0.0740000048","low":"0.0740000048","pool_id":"kujira1gvfjvm09gunj9qkygvzr93ld7hux9nwa9k2t8lug8g46p4x8vt0q3xhu06","target_currency":"stATOM","target_volume":"0.8549870000","ticker_id":"KUJI_stATOM"},{"ask":"1.3420000000","base_currency":"KUJI","base_volume":"0.0000000000","bid":"1.3130000000","high":"0.7150014300","last_price":"0.7150014300","low":"0.7150014300","pool_id":"kujira16f84qasz2nw09cy25nlzxnzxyrnhvvygym74869y5q83pev9rhdsr7emra","target_currency":"stOSMO","target_volume":"0.0000000000","ticker_id":"KUJI_stOSMO"},{"ask":"0.0000435000","base_currency":"SWTH","base_volume":"0.0000000000","bid":"0.0000434000","high":"8.4660097477","last_price":"8.4660097477","low":"8.4660097477","pool_id":"kujira1aqnmhyu37ynf8pm0fedtykzf3clk25ecc0p23cce2d5dc59eteeqgrg6tv","target_currency":"USK","target_volume":"0.0000000000","ticker_id":"SWTH_USK"},{"ask":"0.1600000000","base_currency":"xASTRO","base_volume":"0.0000000000","bid":"0.0510000000","high":"8.4660097477","last_price":"8.4660097477","low":"8.4660097477","pool_id":"kujira1qwtjeaf0y6hn094gn3xprw7wknkl4egpkr7dqu3cljkev5ex4xfqf2h8uc","target_currency":"USK","target_volume":"0.0000000000","ticker_id":"xASTRO_USK"},{"ask":"0.0000000000","base_currency":"ACRE","base_volume":"0.0000000000","bid":"0.0000000000","high":"0.5450000496","last_price":"0.5450000496","low":"0.5450000496","pool_id":"kujira1zumrlzj7ffq0murckuzykgsvcn3xzyvn3e85fxjsymwyhezmkycqtq87zj","target_currency":"USK","target_volume":"0.0000000000","ticker_id":"ACRE_USK"},{"ask":"0.0020300000","base_currency":"GRAV","base_volume":"41008.8733130000","bid":"0.0019900000","high":"0.0020299999","last_price":"0.0020299949","low":"0.0019900000","pool_id":"kujira1jlyyyg0m649v75nqzm40jfdmjar9sf7rh3qnuz8yqa4345s9tqvqhxwxjq","target_currency":"USK","target_volume":"82.8686240000","ticker_id":"GRAV_USK"},{"ask":"0.9240000000","base_currency":"axlUSDT","base_volume":"0.0000000000","bid":"0.9200000000","high":"8.4660097477","last_price":"8.4660097477","low":"8.4660097477","pool_id":"kujira1kjmu97hr6tvk6m30sjzfm8tj6kzxpprdfssa99jd675u90sfvtdsf36lu7","target_currency":"USK","target_volume":"0.0000000000","ticker_id":"axlUSDT_USK"},{"ask":"0.9953000000","base_currency":"STINJ","base_volume":"0.0000000000","bid":"0.9806000000","high":"8.4660097477","last_price":"8.4660097477","low":"8.4660097477","pool_id":"kujira1te7w4e9w0gqakaxhakqs2k2gqmtnfgx36qh9zadh2yxl750c369qfu7uxl","target_currency":"INJ","target_volume":"0.0000000000","ticker_id":"STINJ_INJ"},{"ask":"1.0390000000","base_currency":"ampWHALE","base_volume":"0.0000000000","bid":"1.0170000000","high":"0.7150014300","last_price":"0.7150014300","low":"0.7150014300","pool_id":"kujira10vkk8ulf3rvfuzlfpqflklr2zkq6586pl9amcsafp2s6t4j7qn7seemml3","target_currency":"WHALE","target_volume":"0.0000000000","ticker_id":"ampWHALE_WHALE"},{"ask":"0.0590000000","base_currency":"stOSMO","base_volume":"0.0000000000","bid":"0.0580000000","high":"0.7150014300","last_price":"0.7150014300","low":"0.7150014300","pool_id":"kujira1625a0ks8ceawxsu2am5xxpwtej87h0t3hguqu4rxuq37vgn6lnqsrrqkq0","target_currency":"stATOM","target_volume":"0.0000000000","ticker_id":"stOSMO_stATOM"},{"ask":"0.0004000000","base_currency":"DVPN","base_volume":"0.0000000000","bid":"0.0003950000","high":"8.4660097477","last_price":"8.4660097477","low":"8.4660097477","pool_id":"kujira1ullqzk95uh0derdqpp8e5f4ukdun00xdal486zmjeeqsfhefgd0qh0qndl","target_currency":"USK","target_volume":"0.0000000000","ticker_id":"DVPN_USK"},{"ask":"1.3908000000","base_currency":"RATOM","base_volume":"0.0000000000","bid":"1.3605000000","high":"8.4660097477","last_price":"8.4660097477","low":"8.4660097477","pool_id":"kujira1ryul6unmsnjccsugtempgdtly3gsdtu8af44yt5sqf4zpkgg7vjqkpxjjx","target_currency":"ATOM","target_volume":"0.0000000000","ticker_id":"RATOM_ATOM"},{"ask":"0.5710000000","base_currency":"stOSMO","base_volume":"0.0000000000","bid":"0.5590000000","high":"8.1940568957","last_price":"8.1940568957","low":"8.1940568957","pool_id":"kujira1yugk2n5y5059yzr7yq938nwzkz9mjgfctunhjhf0jp8tgax7t2cqag6e8c","target_currency":"axlUSDC","target_volume":"0.0000000000","ticker_id":"stOSMO_axlUSDC"},{"ask":"0.5970000000","base_currency":"stOSMO","base_volume":"0.0000000000","bid":"0.5840000000","high":"8.4660097477","last_price":"8.4660097477","low":"8.4660097477","pool_id":"kujira1tnnvtvere0pwz0uupy4crl3dv6yszte9nqms4fwmfhj3e2yl477sa0frks","target_currency":"USK","target_volume":"0.0000000000","ticker_id":"stOSMO_USK"},{"ask":"0.1868000000","base_currency":"RAC","base_volume":"117.7351570000","bid":"0.1831000000","high":"0.1906000019","last_price":"0.1906000019","low":"0.1868000016","pool_id":"kujira1kmw6fk5p7an27u8f3er08xrwvzlehczymgshkqxzfrxyrfleu2eqxykaln","target_currency":"USK","target_volume":"22.2154960000","ticker_id":"RAC_USK"},{"ask":"2.0000000000","base_currency":"REGEN","base_volume":"0.0000000000","bid":"0.0100000000","high":"8.4660097477","last_price":"8.4660097477","low":"8.4660097477","pool_id":"kujira1p2vmq7g8fghkeak0hz4qfgeskkd7zqp3vnj6m3sa0r6gp4dr37usmtgtej","target_currency":"USK","target_volume":"0.0000000000","ticker_id":"REGEN_USK"},{"ask":"0.1100000000","base_currency":"SOMM","base_volume":"0.0000000000","bid":"0.1240000000","high":"8.4660097477","last_price":"8.4660097477","low":"8.4660097477","pool_id":"kujira1wckallump2k4284pt5wqg63a8prr205y532ym3850l82k75yzems5mfnkj","target_currency":"USK","target_volume":"0.0000000000","ticker_id":"SOMM_USK"},{"ask":"0.0490000000","base_currency":"FLIX","base_volume":"40.9999900000","bid":"0.0480000000","high":"0.0510000253","last_price":"0.0490000188","low":"0.0480000011","pool_id":"kujira1uau4ctnpfze4qqljqgup3watfg9yvmkgr7gevzgv27g30yx56fvsr6dkqx","target_currency":"USK","target_volume":"1.9777810000","ticker_id":"FLIX_USK"},{"ask":"0.6320000000","base_currency":"AKT","base_volume":"0.0000000000","bid":"0.6200000000","high":"8.4660097477","last_price":"8.4660097477","low":"8.4660097477","pool_id":"kujira1ppr63x265m0sgqdhl2k23t8hmfcgrar85rxgq45uvctksr8w8hzsqwwdcq","target_currency":"USK","target_volume":"0.0000000000","ticker_id":"AKT_USK"},{"ask":"0.0002400000","base_currency":"MNTL","base_volume":"0.0000000000","bid":"0.0002400000","high":"8.4660097477","last_price":"8.4660097477","low":"8.4660097477","pool_id":"kujira1vpvt27kwaasyfxyd9lkfu3xlm3axmayg40z8reas7l7nk659kcqsgywtdv","target_currency":"USK","target_volume":"0.0000000000","ticker_id":"MNTL_USK"},{"ask":"0.1995000000","base_currency":"CRE","base_volume":"0.0000000000","bid":"0.0050000000","high":"8.4660097477","last_price":"8.4660097477","low":"8.4660097477","pool_id":"kujira1nu8kef49y0pdrkphtkt857tgtt0pe8nr8ms0pnp6lylrav9jq2asmjljhe","target_currency":"USK","target_volume":"0.0000000000","ticker_id":"CRE_USK"},{"ask":"0.0024990000","base_currency":"WINK","base_volume":"64311.9827560000","bid":"0.0022560000","high":"0.0024990000","last_price":"0.0024940000","low":"0.0022560000","pool_id":"kujira1qxtd87qus6uzvqs4jv9r0j9ccd4yla42s6qag7y8fp7hhv68nzas6hqxgw","target_currency":"USK","target_volume":"160.0058490000","ticker_id":"WINK_USK"},{"ask":"0.1466000000","base_currency":"MNTA","base_volume":"35312.9424800000","bid":"0.1434000000","high":"0.1488000000","last_price":"0.1442000001","low":"0.1406000000","pool_id":"kujira1ws9w7wl68prspv3rut3plv8249rm0ea0kk335swye3sl2slld4lqdmc0lv","target_currency":"axlUSDC","target_volume":"5104.8720160000","ticker_id":"MNTA_axlUSDC"},{"ask":"0.1960000000","base_currency":"MNTA","base_volume":"24254.3543210000","bid":"0.1920000000","high":"0.1959999995","last_price":"0.1959999950","low":"0.1879999993","pool_id":"kujira1nkgq8xl4flsau7v3vphr3ayc7tprgazg6pzjmq8plkr76v385fhsx26qfa","target_currency":"KUJI","target_volume":"4672.5656000000","ticker_id":"MNTA_KUJI"},{"ask":"0.0011327000","base_currency":"GLTO","base_volume":"187579.1815480000","bid":"0.0010857000","high":"0.0011310996","last_price":"0.0011310996","low":"0.0010148908","pool_id":"kujira1cxvcx9e0se7xg7xgrx806kd0g0x4ugc6weg4nur8fuq5m33q4ckqu4j56e","target_currency":"USK","target_volume":"197.4620240000","ticker_id":"GLTO_USK"},{"ask":"0.0125000000","base_currency":"TORI","base_volume":"0.0000000000","bid":"0.5000000000","high":"8.4660097477","last_price":"8.4660097477","low":"8.4660097477","pool_id":"kujira1n2xz4et7gpge8e6dml2z2n8pqa944gz4l3yvhtt7avr5dah0n3rs5jzmvh","target_currency":"USK","target_volume":"0.0000000000","ticker_id":"TORI_USK"},{"ask":"0.1070000000","base_currency":"ARCH","base_volume":"7733.4220470673","bid":"0.1035000000","high":"0.1101998501","last_price":"0.1066999938","low":"0.0973000000","pool_id":"kujira1dfafpr32hrrue43373gvnjs93gzdyuqh6rcjv23scfztu354fxdqhzvfrv","target_currency":"USK","target_volume":"809.4715530000","ticker_id":"ARCH_USK"},{"ask":"2129.2900000000","base_currency":"wstETH","base_volume":"0.0000000000","bid":"2040.9000000000","high":"715001430002.8600000000","last_price":"715001430002.8600000000","low":"715001430002.8600000000","pool_id":"kujira140mxwk6w70yhrgumc0fv62p6aptgwx8t3eh9v08nq252dc5ur6qsyw6gg5","target_currency":"USK","target_volume":"0.0000000000","ticker_id":"wstETH_USK"},{"ask":"0.0732000000","base_currency":"STARS","base_volume":"65688.1907980000","bid":"0.0716000000","high":"0.0733999999","last_price":"0.0718000000","low":"0.0718000000","pool_id":"kujira1hsdzhyvuc2z3f8d3yae84uk62d69vk68vxgudkun7gccz6hvrvfq0vx6fd","target_currency":"MNTA","target_volume":"4773.2396690000","ticker_id":"STARS_MNTA"},{"ask":"1.1364000000","base_currency":"wstETH","base_volume":"0.0000000000","bid":"1.1307000000","high":"0.9682000430","last_price":"0.9682000430","low":"0.9682000430","pool_id":"kujira1ehwsdvgs3chpxuexktymjmmjj68m3h4q67p9vjj9rrgjqycc3gtsfzej24","target_currency":"wETH","target_volume":"0.0000000000","ticker_id":"wstETH_wETH"}]}
